README.md
setup.py
awselkcli/__init__.py
awselkcli/elk.py
awselkcli/logSystem.py
awselkcli.egg-info/PKG-INFO
awselkcli.egg-info/SOURCES.txt
awselkcli.egg-info/dependency_links.txt
awselkcli.egg-info/requires.txt
awselkcli.egg-info/top_level.txt