Metadata-Version: 1.1
Name: awselkcli
Version: 1.7
Summary: All the AWS functionality we use in our projects
Home-page: UNKNOWN
Author: Benlolo Noam
Author-email: UNKNOWN
License: Apache Software License
Keywords: AWS utils cli wrapper
Platform: UNKNOWN
Classifier: Development Status :: 3 - Alpha
Classifier: Programming Language :: Python :: 3.7
